[
  {
    "address": "13EyMuuDHwtq5RD6w3psCJ9WvJFZzDDion6Fd2FVAqxz1g7K",
    "name": "ChaosDAO OpenGov",
    "image": "",
    "shortDescription": "",
    "longDescription": ""
  },
  {
    "address": "1jPw3Qo72Ahn7Ynfg8kmYNLEPvHWHhPfPNgpJfp5bkLZdrF",
    "name": "JimmyTudeski - Polkadot Resident",
    "image": "",
    "shortDescription": "",
    "longDescription": ""
  },
  {
    "address": "15fTH34bbKGMUjF1bLmTqxPYgpg481imThwhWcQfCyktyBzL",
    "name": "JimmyTudeski - Polkadot Resident",
    "image": "",
    "shortDescription": "",
    "longDescription": ""
  },
  {
    "address": "12s6UMSSfE2bNxtYrJc6eeuZ7UxQnRpUzaAh1gPQrGNFnE8h",
    "name": "Polkadotters",
    "image": "",
    "shortDescription": "",
    "longDescription": ""
  },
  {
    "address": "153YD8ZHD9dRh82U419bSCB5SzWhbdAFzjj4NtA5pMazR2yC",
    "name": "SAXEMBERG",
    "image": "",
    "shortDescription": "",
    "longDescription": ""
  },
  {
    "address": "1ZSPR3zNg5Po3obkhXTPR95DepNBzBZ3CyomHXGHK9Uvx6w",
    "name": "William",
    "image": "",
    "shortDescription": "",
    "longDescription": ""
  },
  {
    "address": "12mP4sjCfKbDyMRAEyLpkeHeoYtS5USY4x34n9NMwQrcEyoh",
    "name": "Polkaworld",
    "image": "",
    "shortDescription": "",
    "longDescription": ""
  }
]